MANIFEST.in
setup.cfg
setup.py
docindexer/__init__.py
docindexer/extractor.py
docindexer/indexer.py
docindexer.egg-info/PKG-INFO
docindexer.egg-info/SOURCES.txt
docindexer.egg-info/dependency_links.txt
docindexer.egg-info/not-zip-safe
docindexer.egg-info/requires.txt
docindexer.egg-info/top_level.txt
docindexer/tika/__init__.py