Metadata-Version: 1.1
Name: docindexer
Version: 0.1.dev6
Summary: Document indexer for multiple file formats.
Home-page: https://bitbucket.org/hjalves/docindexer
Author: Humberto Alves
Author-email: hjalves@student.dei.uc.pt
License: GPL
Keywords: document indexer
Platform: UNKNOWN
Classifier: Development Status :: 2 - Pre-Alpha
Classifier: Programming Language :: Python :: 2.7
